uid_check_austria/__init__.py
uid_check_austria/__init__conf__.py
uid_check_austria/__main__.py
uid_check_austria/_datetime_utils.py
uid_check_austria/behaviors.py
uid_check_austria/cli.py
uid_check_austria/config.py
uid_check_austria/config_deploy.py
uid_check_austria/config_show.py
uid_check_austria/defaultconfig.toml
uid_check_austria/enums.py
uid_check_austria/i18n.py
uid_check_austria/logging_setup.py
uid_check_austria/mail.py
uid_check_austria/py.typed
uid_check_austria/adapters/__init__.py
uid_check_austria/adapters/cache/__init__.py
uid_check_austria/adapters/cache/file_cache.py
uid_check_austria/adapters/finanzonline/__init__.py
uid_check_austria/adapters/finanzonline/session_client.py
uid_check_austria/adapters/finanzonline/uid_query_client.py
uid_check_austria/adapters/notification/__init__.py
uid_check_austria/adapters/notification/email_adapter.py
uid_check_austria/adapters/output/__init__.py
uid_check_austria/adapters/output/formatters.py
uid_check_austria/adapters/ratelimit/__init__.py
uid_check_austria/adapters/ratelimit/rate_limit_tracker.py
uid_check_austria/application/__init__.py
uid_check_austria/application/ports.py
uid_check_austria/application/use_cases.py
uid_check_austria/defaultconfig.d/20-email.toml
uid_check_austria/defaultconfig.d/30-logging.toml
uid_check_austria/domain/__init__.py
uid_check_austria/domain/errors.py
uid_check_austria/domain/models.py
uid_check_austria/domain/return_codes.py
uid_check_austria/locales/messages.pot
uid_check_austria/locales/de/LC_MESSAGES/messages.mo
uid_check_austria/locales/de/LC_MESSAGES/messages.po
uid_check_austria/locales/es/LC_MESSAGES/messages.mo
uid_check_austria/locales/es/LC_MESSAGES/messages.po
uid_check_austria/locales/fr/LC_MESSAGES/messages.mo
uid_check_austria/locales/fr/LC_MESSAGES/messages.po
uid_check_austria/locales/ru/LC_MESSAGES/messages.mo
uid_check_austria/locales/ru/LC_MESSAGES/messages.po
uid_check_austria-1.0.0.dist-info/METADATA
uid_check_austria-1.0.0.dist-info/WHEEL
uid_check_austria-1.0.0.dist-info/entry_points.txt
uid_check_austria-1.0.0.dist-info/licenses/LICENSE
uid_check_austria-1.0.0.dist-info/RECORD
