Metadata-Version: 2.4
Name: uid_check_austria
Version: 1.0.0
Summary: Python library and CLI for querying Level 2 UID checks via FinanzOnline Austria
Project-URL: Homepage, https://github.com/bitranox/uid_check_austria
Project-URL: Repository, https://github.com/bitranox/uid_check_austria.git
Project-URL: Issues, https://github.com/bitranox/uid_check_austria/issues
Author-email: bitranox <bitranox@gmail.com>
License: MIT
License-File: LICENSE
Keywords: austria,cli,finanzonline,tax,uid,vat,verification
Classifier: Environment :: Console
Classifier: License :: OSI Approved :: MIT License
Classifier: Operating System :: OS Independent
Classifier: Programming Language :: Python :: 3
Classifier: Programming Language :: Python :: 3 :: Only
Classifier: Programming Language :: Python :: 3.10
Classifier: Programming Language :: Python :: 3.11
Classifier: Programming Language :: Python :: 3.12
Classifier: Programming Language :: Python :: 3.13
Classifier: Typing :: Typed
Requires-Python: >=3.10
Requires-Dist: btx-lib-mail>=1.0.3
Requires-Dist: filelock>=3.20.1
Requires-Dist: lib-cli-exit-tools>=2.2.3
Requires-Dist: lib-layered-config>=5.1.0
Requires-Dist: lib-log-rich>=6.0.0
Requires-Dist: orjson>=3.11.5
Requires-Dist: rich-click>=1.9.4
Requires-Dist: zeep>=4.3.2
Provides-Extra: dev
Requires-Dist: bandit>=1.9.2; extra == 'dev'
Requires-Dist: build>=1.3.0; extra == 'dev'
Requires-Dist: codecov-cli>=11.2.6; extra == 'dev'
Requires-Dist: import-linter>=2.9; extra == 'dev'
Requires-Dist: pip-audit>=2.10.0; extra == 'dev'
Requires-Dist: pyright>=1.1.407; extra == 'dev'
Requires-Dist: pytest-cov>=7.0.0; extra == 'dev'
Requires-Dist: pytest>=9.0.2; extra == 'dev'
Requires-Dist: rtoml>=0.13.0; extra == 'dev'
Requires-Dist: ruff>=0.14.10; extra == 'dev'
Requires-Dist: textual>=6.11.0; extra == 'dev'
Requires-Dist: twine>=6.2.0; extra == 'dev'
